{
  "slug": "corn-on-the-cob-holders-for-restaurants",
  "title": "Corn on the Cob Holders for Restaurants",
  "keyword": "corn on the cob holders for restaurants",
  "meta_description": "Upgrade your service with the best corn on the cob holders for restaurants. Discover durable, dishwasher-safe options that improve efficiency and guest experien",
  "html": "<p>If you run a busy eatery, whether it’s a smokehouse, a seaside clam shack, or a bustling barbecue joint, you know that side dishes can make or break the flow of service. Corn on the cob is a crowd favorite, but without the right tools, it can become a logistical nightmare. It’s messy, hot, and difficult for guests to handle gracefully. That is why investing in high-quality <strong>corn on the cob holders for restaurants</strong> is essential for maintaining a clean dining room and a happy kitchen staff.</p>\n\n<h2>Why Commercial Kitchens Need Specific Tools</h2>\n\n<p>It might be tempting to grab the cheapest plastic skewers available from a discount store, but those rarely hold up in a commercial environment. In a restaurant setting, volume is high, and turnover is fast. You need equipment that can withstand repeated use, high-temperature dishwashing, and the occasional drop on a hard kitchen floor. Standard home-use holders often bend or rust after a few runs through the industrial dishwasher. When sourcing <strong>corn on the cob holders for restaurants</strong>, you are looking for three things: durability, ease of cleaning, and safety.</p>\n\n<p>Beyond durability, there is the matter of presentation. Nothing looks less professional than a bent, rusty skewer arriving at a table. Furthermore, efficiency is key. If your prep staff is struggling to insert dull plastic points into the corn, you are losing valuable labor minutes every day. Robust stainless steel prongs glide in effortlessly, speeding up the prep process during the dinner rush.</p>\n\n<h2>The Storage Revolution: Interlocking Design</h2>\n\n<p>One of the biggest headaches for chefs and kitchen managers is storage. Corn skewers are notoriously difficult to organize. If you throw them loose into a container, they become a tangled nest of sharp metal points. This is frustrating for staff trying to grab a pair quickly, and it poses a genuine safety hazard. Reaching into a bin to retrieve a skewer shouldn't result in a puncture wound.</p>\n\n<p>This is where thoughtful design truly shines. The <strong>Girla Interlocking Corn on the Cob Holders Set</strong> offers a brilliant solution to this specific problem. As the name suggests, these holders are designed to interlock with one another. The two skewers in a pair snap together neatly. This means they stay paired during washing, storage, and service. No more digging for a matching handle or risking a finger prick. By keeping them locked together, you maintain a tidy utensil drawer and a safer workstation.</p>\n\n<h2>Hygiene and Dishwasher Safety</h2>\n\n<p>In the foodservice industry, sanitation is non-negotiable. Corn holders have small nooks and crannies where corn residue and butter can hide. If they aren’t dishwasher safe, they become a breeding ground for bacteria. Hand-washing dozens of tiny corn skewers at the end of a shift is not a good use of your staff's time.</p>\n\n<p>You need gear that can handle the heat and pressure of a commercial dishwasher. The <strong>Girla Interlocking Corn on the Cob Holders Set</strong> is constructed with this in mind. They are fully dishwasher-safe, ensuring they come out sanitized and ready for the next service. The stainless steel prongs resist rust and corrosion, while the silicone handles are durable enough to withstand high-temperature wash cycles without cracking or fading.</p>\n\n<h2>Enhancing the Guest Experience</h2>\n\n<p>While the back-of-house benefits are clear, the front-of-house impact is just as important. Eating corn on the cob can be a slippery, buttery endeavor. Guests appreciate having a secure grip on their food. It keeps their fingers clean, which is particularly important if they are eating finger foods like ribs or wings alongside their corn.</p>\n\n<p>The handles on the <strong>Girla Interlocking Corn on the Cob Holders Set</strong> feature bright silicone grips. This isn't just for aesthetics; the silicone provides excellent traction even when coated in butter. For restaurants, this means fewer dropped cobs and less mess on the table or floor. Additionally, the bright colors add a pop of fun to the table setting, signaling to the guest that you have provided a tool specifically for their comfort.</p>\n\n<h2>Operational Efficiency Tips</h2>\n\n<p>Implementing a new tool in your kitchen requires a small adjustment to your workflow. Here are a few practical tips to get the most out of your corn skewers:</p>\n\n<ol>\n  <li><strong>Pre-insert during prep:</strong> Don't leave this to the servers or the guests. Have your prep team insert the holders after the corn is boiled and before it is buttered and placed on the line. This keeps the line moving fast.</li>\n  <li><strong>Color coding:</strong> If you use different colored sets, you can assign specific colors to specific shifts or tables, though for most general use, a uniform mix works perfectly fine.</li>\n  <li><strong>Storage bins:</strong> Since the Girla holders interlock, they can be stacked neatly in a dedicated storage bin rather than tossed in a pile.</li>\n  <li><strong>Inspect regularly:</strong> Even high-quality stainless steel can take a beating. Have your staff check the tightness of the handles periodically to ensure they remain secure.</li>\n</ol>\n\n<h2>FAQ</h2>\n\n<h3>Are metal corn holders better than plastic for restaurants?</h3>\n<p>Yes, absolutely. Metal holders are far more durable and offer better penetration into the cob, especially when the corn is fresh and dense. Plastic prongs tend to bend or break after a few uses, whereas high-quality stainless steel lasts for years.</p>\n\n<h3>How do I prevent corn holders from getting lost in the dishwasher?</h3>\n<p>This is a common issue, but it is easily solved by using interlocking holders. Because the pairs snap together, they are too large to fall through the gaps of a standard dishwasher rack. They stay put throughout the wash cycle.</p>\n\n<h3>Can silicone handles withstand high heat?</h3>\n<p>Silicone is heat-resistant and generally handles temperatures well above what you would find in a standard dishwasher or even a hot holding cabinet. However, they should not be exposed directly to an open flame or placed inside an oven while the corn is cooking.</p>",
  "type": "product",
  "product": "B0D129D2HH",
  "model": "cerebras:zai-glm-4.7"
}