{
  "slug": "how-to-make-sweet-and-spicy-pineapple-al-pastor-skewers-at-home",
  "title": "How to Make Sweet‑And‑Spicy Pineapple Al Pastor Skewers at Home",
  "keyword": "sweet and spicy pineapple al pastor skewers",
  "meta_description": "Master sweet and spicy pineapple al pastor skewers at home using a vertical gyro pan. This recipe brings authentic taco night flavor to your kitchen.",
  "html": "<p>There is nothing quite like the aroma of marinated pork roasting with a hint of fruit and chili. While grabbing street tacos is easy, recreating that specific trompo-style flavor at home usually feels impossible without a commercial rotisserie. However, if you’ve been craving authentic Mexican street food, learning how to make <strong>sweet and spicy pineapple al pastor skewers</strong> in your own kitchen is a game changer. With the right technique and a specific piece of gear, you can achieve that tender, caramelized texture without needing a vertical spit the size of a refrigerator.</p>\n\n<h2>The Secret to Authentic Al Pastor at Home</h2>\n\n<p>The defining characteristic of al pastor is the way the meat cooks on a vertical spit, allowing the fat to drip down and baste the pork as it crisps. Since most of us don’t have room for a trompo in our apartments or backyards, we have to mimic this vertical geometry. This is where the <strong>Vertical Gyro Pan with Skewer for Oven</strong> becomes essential. This stainless steel vertical skewer pan for oven-roasted gyros, al pastor tacos, shawarma, and kebabs solves the spatial problem by stacking the meat upright.</p>\n\n<p>By using this pan, the heat circulates around the meat similarly to a commercial rotisserie. As the pork cooks, the juices run down the stack, keeping the meat moist while the exterior gets a fantastic char. It is the single most effective tool for transforming a standard pork shoulder into something that tastes like it came from a taco truck in Mexico City.</p>\n\n<h2>Building the Perfect Marinade</h2>\n\n<p>You cannot have good al pastor without a heavy dose of adobo. The flavor profile needs to strike a balance between the savory richness of pork and the bright tang of pineapple. While some recipes use just dried chilies, I prefer a wet marinade that penetrates the meat fibers deeply.</p>\n\n<p>The base of your marinade should include dried guajillo or ancho chilies rehydrated in hot water. To this, you add achiote paste for that signature deep red color and earthy flavor. The sweetness comes from pineapple juice, which also serves a functional purpose: the enzymes in the fruit help break down the tough connective tissue in the pork shoulder.</p>\n\n<p>For the spicy kick, don't shy away from chipotle peppers in adobo sauce. They add a smoky heat that pairs perfectly with the fruit. To round it out, blend in white vinegar, cumin, oregano, a pinch of cloves, and plenty of garlic and onion powder.</p>\n\n<ul>\n    <li>3-4 Dried Guajillo chilies (stems removed)</li>\n    <li>1/4 cup Achiote paste</li>\n    <li>1 cup Pineapple juice</li>\n    <li>2 Chipotle peppers in adobo sauce</li>\n    <li>1 tbsp White vinegar</li>\n    <li>1 tsp Cumin and dried oregano</li>\n    <li>Salt and pepper to taste</li>\n</ul>\n\n<h2>Assembling Sweet and Spicy Pineapple Al Pastor Skewers</h2>\n\n<p>Preparation is key for these <strong>sweet and spicy pineapple al pastor skewers</strong>. You need to start with a boneless pork shoulder, also known as a Boston butt. Trim the excess fat cap, but leave about a quarter-inch on to keep the meat juicy. The most critical step here is slicing. You want to cut the pork into very thin slices, about 1/8 to 1/4 of an inch thick. If the meat is too thick, it won't cook through before the outside burns.</p>\n\n<p>Toss your sliced pork thoroughly in the marinade. Let it sit in the refrigerator for at least four hours, though overnight is ideal. When you are ready to cook, take out your <strong>Gyro Pan with Skewer for Oven</strong>. You will want to stack the meat onto the central skewer, pressing it down tightly to form a solid tower of pork. Intersperse slices of fresh pineapple between the layers of meat. This ensures that as the pineapple roasts, its sweetness infuses directly into the pork.</p>\n\n<h2>Roasting Techniques for Maximum Caramelization</h2>\n\n<p>Preheat your oven to a high temperature—around 400°F (200°C). Place the loaded vertical skewer pan on the middle rack. The high heat is necessary to render the fat quickly and create the crisp edges associated with street tacos. Roast the stack for about 60 to 75 minutes.</p>\n\n<p>Halfway through the cooking process, open the oven and carefully baste the outside of the meat stack with the drippings collected at the bottom of the pan. This adds an extra layer of flavor and shine. Once the meat is cooked through and the exterior is browned and crispy, remove it from the oven. Let it rest for about 10 minutes. This rest period allows the juices to redistribute so they don't run out the moment you start slicing.</p>\n\n<h2>Serving Your Tacos</h2>\n\n<p>To serve, use a sharp knife to shave the meat off the vertical stack, slicing it thinly against the grain. You want a mix of the crispy exterior pieces and the tender interior meat. Serve these on small, warm corn tortillas with diced white onions, fresh cilantro, and a squeeze of lime. A final addition of small, grilled chunks of pineapple on top of the taco is non-negotiable for that complete sweet-and-spicy experience.</p>\n\n<h2>FAQ</h2>\n\n<h3>Can I use a different cut of meat for this recipe?</h3>\n<p>Technically, you can use pork loin, but it is not recommended. Pork loin is much leaner than shoulder and lacks the intramuscular fat needed to keep the tacos moist during the roasting process. If you use loin, the meat tends to become dry and tough, whereas the shoulder breaks down beautifully and becomes tender.</p>\n\n<h3>Do I need the vertical gyro pan to make this?</h3>\n<p>While you can cook marinated pork on a standard baking sheet, you won't achieve the same texture. The <strong>Vertical Gyro Pan with Skewer for Oven</strong> is crucial because it allows the fat to render down through the meat, basting it as it cooks. Laying the meat flat in a pan results in a stew-like texture rather than the crisp, shaved edges of true al pastor.</p>\n\n<h3>How spicy is this recipe?</h3>\n<p>The heat level is adjustable. The combination of guajillo chilies and chipotle peppers provides a medium heat level with a smoky profile. If you prefer a milder flavor, remove the seeds from the dried chilies before soaking them and reduce the amount of chipotle peppers. If you love heat, you can add a teaspoon of crushed red pepper flakes to the marinade.</p>",
  "type": "product",
  "product": "B0DX2G24HD",
  "model": "cerebras:zai-glm-4.7"
}