{
  "slug": "using-umbrella-straws-to-elevate-your-home-bar-s-instagram-look",
  "title": "Using Umbrella Straws to Elevate Your Home Bar’s Instagram Look",
  "keyword": "umbrella straws home bar instagram",
  "meta_description": "Transform your cocktails with umbrella straws. Learn how to style your home bar drinks for the perfect Instagram shot using these tropical essentials.",
  "html": "<p>We’ve all been there—you mix a perfectly balanced margarita, balance a lime wedge on the rim, and snap a photo, only to realize the drink looks a bit flat against the glass. If you are looking to boost your engagement and add a pop of personality to your feed, using <strong>umbrella straws home bar instagram</strong> styling is the quickest path to a viral aesthetic. It’s not just about the recipe; it’s about the narrative you build around the glass.</p>\n\n<h2>The Psychology of a Pretty Drink</h2>\n<p>There is a reason why tropical drinks are the kings of social media. Humans are visually wired to respond to color and contrast. A clear glass filled with amber rum and bright orange juice is nice, but add a miniature parasol, and suddenly the drink has a focal point. It tells a story of vacation, relaxation, and fun. When you are setting up your home bar, you aren't just mixing liquids; you are curating an experience. The garnish is the exclamation point at the end of that sentence.</p>\n\n<h2>Elevating Your Umbrella Straws Home Bar Instagram Game</h2>\n<p>The trick to a great photo isn't just buying any old decorations; it is about cohesion. This is where the right tools make all the difference. I recently started using the <strong>100PCS Umbrella Straw, Drink Umbrellas for Hawaiian, Tropical, Luau, Tiki Party</strong> pack for my summer get-togethers, and it solved a major logistical problem. Usually, you have to buy a box of straws and a separate pack of little umbrellas, and then you have to fiddle around trying to get them to stay put on the rim of the glass.</p>\n\n<p>With these <strong>100-Pack Umbrella Straws</strong>, the decoration is built right into the drinking vessel. This ensures the umbrella is perfectly positioned every time, sticking straight up or at a jaunty angle without sliding down into the drink. For Instagram purposes, this consistency is gold. You can line up three different cocktails—maybe a Mai Tai, a Piña Colada, and a Blue Hawaiian—and the uniformity of the straws creates a visually satisfying grid pattern that looks incredibly professional.</p>\n\n<h2>Lighting and Composition Tips</h2>\n<p>Once you have your <strong>100-Pack Umbrella Straws</strong> ready, you need to know how to light them. These mini parasols usually feature paper or bamboo construction, which looks fantastic under natural light. Avoid using the harsh flash on your phone, as it will blow out the bright colors of the umbrella.</p>\n\n<p>Instead, set your drink near a window with indirect daylight. The light should catch the paper ribs of the umbrella, creating texture and depth in your photo. If you are shooting at night, use a ring light or a small LED panel positioned to the side of the glass rather than directly behind the camera. This highlights the curve of the glass and the vibrant colors of the <strong>100PCS Umbrella Straw, Drink Umbrellas for Hawaiian, Tropical, Luau, Tiki Party</strong> set against the liquid.</p>\n\n<h2>Essential Drinks for Your Parasol Collection</h2>\n<p>Not every drink deserves an umbrella. You generally want to save these for drinks that are fruity, frozen, or served in highball glasses. Using a disposable straw with a built-in mini parasol implies a sense of casual fun, so save your stirred bourbon and your neat whiskey for a different aesthetic.</p>\n\n<p>Here are the top five recipes that pair perfectly with umbrella straws to maximize your likes:</p>\n\n<ol>\n  <li><strong>Classic Piña Colada:</strong> The white cream of the coconut contrasts beautifully with colorful paper umbrellas.</li>\n  <li><strong>Mai Tai:</strong> The dark rum and red cherry float need a bright accent to break up the darkness.</li>\n  <li><strong>Mojito:</strong> The green mint looks crisp against a yellow or pink umbrella.</li>\n  <li><strong>Blue Hawaiian:</strong> Blue drinks can look artificial on camera; a natural bamboo/paper umbrella grounds the color palette.</li>\n  <li><strong>Rum Runner:</strong> A complex, dark fruit drink that benefits from the festive lift of a parasol.</li>\n</ol>\n\n<h2>Hosting with Bulk Utility</h2>\n<p>When you are hosting a pool party or a luau, the last thing you want to do is hand-wash delicate garnishes. The beauty of the <strong>100-Pack Umbrella Straws</strong> is that they are disposable. You get the visual impact of a tiki bar without the cleanup headache. Because the pack comes with 100 pieces, you have enough for a large crowd, meaning you can keep the drinks flowing without constantly running to the store for more supplies. Plus, having a bulk supply on hand encourages creativity—you might find yourself putting umbrellas in iced tea or lemonade just to keep the vibe going long after the cocktail hour is over.</p>\n\n<h2>FAQ</h2>\n\n<h3>Are these straws sturdy enough for thick frozen drinks?</h3>\n<p>Yes, these disposable drinking straws are designed to handle standard frozen cocktails like margaritas and slushies. However, they are plastic, so avoid using them for excessively thick ice creams or milkshakes that require heavy suction.</p>\n\n<h3>Can the umbrellas get wet?</h3>\n<p>The mini parasols attached to the straws are made of paper attached to bamboo or plastic picks. They are designed to rest on the rim or sit just inside the liquid. Prolonged submersion might cause the paper to sag slightly, but for the duration of a drink, they hold up perfectly fine.</p>\n\n<h3>Do the straws come in different colors?</h3>\n<p>The <strong>100PCS Umbrella Straw, Drink Umbrellas for Hawaiian, Tropical, Luau, Tiki Party</strong> set typically comes in an assortment of vibrant tropical colors. This variety is excellent for photography, as it allows you to mix and match hues to complement the specific ingredients in your cocktail.</p>",
  "type": "product",
  "product": "B0DBH4V77S",
  "model": "cerebras:zai-glm-4.7"
}